config/__init__.py
config/config.py
tradehub/__init__.py
tradehub/tradify.py
tradehub/base_validation/__init__.py
tradehub/base_validation/_orderValidation.py
tradehub/base_validation/checksum.py
tradehub/base_validation/file_read.py
tradehub/base_validation/timestamp.py
GoPocket_pytrade_tradehub_test-1.0.0.dist-info/METADATA
GoPocket_pytrade_tradehub_test-1.0.0.dist-info/WHEEL
GoPocket_pytrade_tradehub_test-1.0.0.dist-info/top_level.txt
GoPocket_pytrade_tradehub_test-1.0.0.dist-info/RECORD
